synse_grpc/__init__.py
synse_grpc/api.py
synse_grpc/client.py
synse_grpc/errors.py
synse_grpc/grpc.py
synse_grpc/synse_pb2.py
synse_grpc/synse_pb2_grpc.py
synse_grpc/utils.py
tests/__init__.py
tests/test_client.py
tests/test_errors.py
tests/test_utils.py
synse_grpc-3.1.0.dist-info/METADATA
synse_grpc-3.1.0.dist-info/WHEEL
synse_grpc-3.1.0.dist-info/top_level.txt
synse_grpc-3.1.0.dist-info/RECORD
