Metadata-Version: 2.1
Name: synse-grpc
Version: 3.1.0
Summary: The Synse gRPC API for plugin communication.
Home-page: https://github.com/vapor-ware/synse-server-grpc
Author: Vapor IO
Author-email: vapor@vapor.io
License: GNU General Public License v3.0
Platform: UNKNOWN
Classifier: Intended Audience :: Developers
Classifier: Natural Language :: English
Classifier: Programming Language :: Python
Classifier: Programming Language :: Python :: 3
Classifier: Programming Language :: Python :: 3.6
Classifier: Programming Language :: Python :: 3.7
Requires-Python: >=3.6
Requires-Dist: grpcio (>=1.8.6)
Requires-Dist: protobuf
